Workbook

Sheet Summary
A1: OMS BA Project - Tracking Summary
A3: Business requirements | B3: =COUNTIF(Requirements!B:B,"Business Requirement") -> 6
A4: Functional requirements | B4: =COUNTIF(Requirements!B:B,"Functional") -> 17
A5: Non-functional requirements | B5: =COUNTIF(Requirements!B:B,"Non-Functional") -> 10
A6: User stories | B6: =COUNTIF('Jira Backlog'!B:B,"Story") -> 17
A7: Total story points (stories+tasks+bugs) | B7: ='Sprint Plan'!E6 -> 139
A8: Test cases | B8: =COUNTA(UAT!A2:A26) -> 25
A9: Passed | B9: =COUNTIF(UAT!H:H,"Pass") -> 21
A10: Failed | B10: =COUNTIF(UAT!H:H,"Fail") -> 4
A11: Pass rate | B11: =B9/B8 -> 0.84
A12: FRs with at least one test case | B12: =SUMPRODUCT(--(COUNTIF(UAT!B2:B26,Requirements!A8:A24)>0)) -> 17
A13: Requirement coverage (FRs tested / FRs) | B13: =B12/B4 -> 1
A14: Open bugs | B14: =COUNTIFS('Jira Backlog'!B:B,"Bug",'Jira Backlog'!J:J,"Open") -> 5
A16: Sheets: Stakeholders | Requirements | User Stories | Jira Backlog | Sprint Plan | UAT | RTM

Sheet Stakeholders
A1: Stakeholder | B1: Role | C1: Influence | D1: Interest | E1: Key needs / concerns | F1: Engagement approach
A2: Customer | B2: End user placing and tracking orders | C2: High | D2: Medium | E2: Fast delivery, no payment failures, clear status, easy refunds | F2: Keep informed (notifications); validated through surveys/UAT personas
A3: Customer Support | B3: Handles complaints and tickets | C3: Medium | D3: High | E3: Single view of order, fewer 'where is my order' tickets | F3: Consult; process owner for FR-14; UAT participant
A4: Operations Manager | B4: Owns delivery SLA and fulfilment performance | C4: High | D4: High | E4: SLA visibility, early delay alerts, carrier accountability | F4: Manage closely; business sponsor
A5: Warehouse Team | B5: Pick, pack, dispatch, stock counts | C5: Medium | D5: High | E5: Accurate stock, clear pick lists, realistic cut-off times | F5: Consult; UAT participant for FR-08/15
A6: Finance | B6: Payments, refunds, reconciliation | C6: High | D6: Medium | E6: Correct refunds, reconciliation, reduced revenue leakage | F6: Manage closely; sign-off on FR-13
A7: Product Manager | B7: Owns roadmap and priorities | C7: High | D7: High | E7: Business value, scope control, release timing | F7: Manage closely; approves BRD and backlog
A8: Developer | B8: Builds the solution | C8: Low | D8: Medium | E8: Clear, testable requirements; stable scope | F8: Keep informed; refinement sessions
A9: QA | B9: Verifies the solution | C9: Low | D9: Medium | E9: Testable acceptance criteria, traceability | F9: Keep informed; owns test cases and RTM execution
A10: Payment Gateway (external) | B10: Third-party payment processing | C10: Medium | D10: Medium | E10: Correct API usage, idempotency, low failure/timeouts | F10: Monitor; SLA/contract; integration spec

Sheet Requirements
A1: ID | B1: Type | C1: Requirement | D1: Linked BR | E1: Priority
A2: BR-01 | B2: Business Requirement | C2: Reduce late deliveries (baseline 24.8% delayed vs. promised date; target <=10%)
A3: BR-02 | B3: Business Requirement | C3: Recover revenue lost to failed payments (baseline 3.0% of orders lost; Net Banking 11.3% attempt failure)
A4: BR-03 | B4: Business Requirement | C4: Make inventory accurate in real time (baseline 26% of SKUs mismatched at audit; target <=5%)
A5: BR-04 | B5: Business Requirement | C5: Give customers and staff full order-status visibility (21% of tickets are 'where is my order')
A6: BR-05 | B6: Business Requirement | C6: Cut avoidable support tickets (baseline 1,081 tickets on 6,000 orders; target -35%)
A7: BR-06 | B7: Business Requirement | C7: Make cancellations, returns and refunds fast and transparent (137 refunds pending; avg refund-delay ticket 4.7 days)
A8: FR-01 | B8: Functional | C8: Create an order as 'Confirmed' only after payment success (or COD confirmation); failed payment leaves order in 'Payment Pending'. | D8: BR-02 | E8: High
A9: FR-02 | B9: Functional | C9: Allow payment retry and switching to an alternate method within 30 minutes without re-entering the cart; payments must be idempotent (no double charge). | D9: BR-02 | E9: High
A10: FR-03 | B10: Functional | C10: Check live stock and reserve quantity at checkout; release the reservation if payment fails or times out. | D10: BR-03 | E10: High
A11: FR-04 | B11: Functional | C11: Block checkout for out-of-stock items and offer 'Notify me' / similar products. | D11: BR-03 | E11: High
A12: FR-05 | B12: Functional | C12: Maintain a single order status lifecycle (Placed > Confirmed > Packed > Shipped > Out for Delivery > Delivered, plus Cancelled/Returned) with a timestamp for every change. | D12: BR-04 | E12: High
A13: FR-06 | B13: Functional | C13: Provide a customer order-tracking page showing current status and estimated delivery date. | D13: BR-04 | E13: High
A14: FR-07 | B14: Functional | C14: Send proactive SMS/e-mail/WhatsApp notifications on every key status change and on any predicted delay. | D14: BR-04 | E14: Medium
A15: FR-08 | B15: Functional | C15: Auto-allocate each order to the nearest warehouse holding stock; alert the warehouse if pick/pack exceeds 24 hours. | D15: BR-01 | E15: High
A16: FR-09 | B16: Functional | C16: Auto-assign a carrier by pincode and performance score and ingest carrier tracking events. | D16: BR-01 | E16: Medium
A17: FR-10 | B17: Functional | C17: Flag any order at risk of missing its promised date (SLA breach) to Operations in real time. | D17: BR-01 | E17: High
A18: FR-11 | B18: Functional | C18: Let customers cancel self-service until the order is shipped; trigger refund automatically. | D18: BR-06 | E18: High
A19: FR-12 | B19: Functional | C19: Let customers raise a return request within 7 days of delivery with reason code and pickup slot. | D19: BR-06 | E19: Medium
... A24: FR-17 | B24: Functional | C24: Keep an audit log of all order, payment and inventory state changes (who/what/when). | D24: BR-04 | E24: Low
A25: NFR-01 | B25: Non-Functional | C25: [Performance] Checkout and order-status pages respond in <=2 seconds for 95% of requests at 500 concurrent users.
A26: NFR-02 | B26: Non-Functional | C26: [Availability] 99.9% monthly uptime for order placement; planned maintenance outside 1-5 AM IST window only.
A27: NFR-03 | B27: Non-Functional | C27: [Scalability] Handle 3x current peak order volume (festival sales) without code change.
A28: NFR-04 | B28: Non-Functional | C28: [Security] PCI-DSS compliant payment handling; card data never stored in OMS; role-based access control.
A29: NFR-05 | B29: Non-Functional | C29: [Data privacy] Customer PII encrypted at rest and in transit; compliant with India's DPDP Act 2023.
A30: NFR-06 | B30: Non-Functional | C30: [Reliability] No order lost on payment-gateway or carrier API failure; retry queue with dead-letter alerts.
A31: NFR-07 | B31: Non-Functional | C31: [Auditability] All status changes retained for 7 years and searchable by order ID.
A32: NFR-08 | B32: Non-Functional | C32: [Usability] Customer can complete tracking/cancellation in <=3 clicks; mobile-first responsive UI.
A33: NFR-09 | B33: Non-Functional | C33: [Integration] REST APIs with versioning for payment gateway, carriers, WMS and notification services.
A34: NFR-10 | B34: Non-Functional | C34: [Reporting latency] Dashboards refresh at most every 15 minutes.

Sheet User Stories
A1: Story ID | B1: Epic | C1: FR | D1: User Story | E1: Acceptance Criteria | F1: Priority | G1: Story Points | H1: Sprint
A2: US-01 | B2: EP-1 | C2: FR-01 | D2: As a customer, I want my order confirmed only after my payment succeeds so that I am never charged for an order that doesn't exist. | E2: AC1: Given payment succeeds, when the gateway returns success, then order status = Confirmed and confirmation is sent within 1 minute. AC2: Given payment fails, when the gateway returns failure, then order stays 'Payment Pending' and is not sent to the warehouse. | F2: High | G2: 5 | H2: Sprint 1
A3: US-02 | B3: EP-1 | C3: FR-02 | D3: As a customer, I want to retry or switch my payment method after a failure so that I don't lose my cart. | E3: AC1: Given a failed payment, when I choose another method within 30 minutes, then the same cart and price are retained. AC2: Given I retry twice quickly, then I am charged only once (idempotency). | F3: High | G3: 8 | H3: Sprint 1
A4: US-03 | B4: EP-2 | C4: FR-03 | D4: As a customer, I want stock checked and held while I pay so that the item I buy is actually available. | E4: AC1: Given stock >= quantity, when I start payment, then quantity is reserved for 15 minutes. AC2: Given payment fails or times out, then the reservation is released automatically. | F4: High | G4: 8 | H4: Sprint 1
A5: US-04 | B5: EP-2 | C5: FR-04 | D5: As a customer, I want to see out-of-stock items clearly so that I can pick an alternative or get notified. | E5: AC1: Given stock = 0, then 'Add to cart' is disabled and 'Notify me' is shown. AC2: Given an item becomes out of stock during checkout, then the order is blocked with a clear message. | F5: High | G5: 3 | H5: Sprint 1
A6: US-05 | B6: EP-3 | C6: FR-05 | D6: As an operations manager, I want a single status lifecycle with timestamps so that I can see where every order is. | E6: AC1: Given any status change, then the new status and timestamp are stored. AC2: Given an invalid transition (e.g. Delivered to Packed), then the system rejects it. | F6: High | G6: 5 | H6: Sprint 2
A7: US-06 | B7: EP-3 | C7: FR-06 | D7: As a customer, I want to track my order status so that I know when my order will arrive. | E7: AC1: Given a logged-in customer, when they open 'My Orders', then they see current status and estimated delivery date. AC2: Given the carrier updates status, then the tracking page reflects it within 15 minutes. | F7: High | G7: 5 | H7: Sprint 2
A8: US-07 | B8: EP-3 | C8: FR-07 | D8: As a customer, I want proactive updates on my order so that I don't have to contact support. | E8: AC1: Given a status change (Shipped, Out for Delivery, Delivered), then an SMS/e-mail is sent within 5 minutes. AC2: Given an order is predicted to be late, then I am notified with a revised date. | F8: Medium | G8: 5 | H8: Sprint 3
A9: US-08 | B9: EP-4 | C9: FR-08 | D9: As a warehouse executive, I want orders auto-allocated to the nearest stocked warehouse so that dispatch is faster. | E9: AC1: Given an order is confirmed, then it is assigned to the nearest warehouse with stock. AC2: Given pick/pack is not complete in 24 hours, then the warehouse manager is alerted. | F9: High | G9: 8 | H9: Sprint 2
A10: US-09 | B10: EP-4 | C10: FR-09 | D10: As an operations manager, I want carriers assigned by pincode performance so that late deliveries reduce. | E10: AC1: Given a shipment is created, then the carrier with the best on-time score for that pincode is assigned. AC2: Given the carrier posts a tracking event, then it is stored against the shipment. | F10: Medium | G10: 8 | H10: Sprint 3
A11: US-10 | B11: EP-4 | C11: FR-10 | D11: As an operations manager, I want to be alerted when an order may miss its promised date so that I can intervene. | E11: AC1: Given an order not shipped 48 hours after confirmation, then it is flagged 'At Risk'. AC2: Given an order is delayed, then it appears on the Ops dashboard with the delay reason. | F11: High | G11: 5 | H11: Sprint 2
A12: US-11 | B12: EP-5 | C12: FR-11 | D12: As a customer, I want to cancel an order before it ships so that I don't pay for something I no longer need. | E12: AC1: Given status is before Shipped, when I cancel, then status = Cancelled and a refund is initiated. AC2: Given status is Shipped or later, then the Cancel button is not available. | F12: High | G12: 5 | H12: Sprint 3
A13: US-12 | B13: EP-5 | C13: FR-12 | D13: As a customer, I want to raise a return request online so that I can send back a wrong or damaged item easily. | E13: AC1: Given an order delivered within the last 7 days, then 'Return' is available with reason selection. AC2: Given I submit a return, then a pickup slot is confirmed. | F13: Medium | G13: 5 | H13: Sprint 3
... A18: US-17 | B18: EP-6 | C18: FR-17 | D18: As an auditor, I want every status change logged so that disputes can be investigated. | E18: AC1: Given any order, payment or inventory change, then who/what/when is logged and cannot be edited. | F18: Low | G18: 3 | H18: Sprint 4

Sheet Jira Backlog
A1: Key | B1: Issue Type | C1: Epic | D1: Parent / Linked | E1: Summary | F1: Priority | G1: Story Points | H1: Sprint | I1: Assignee (role) | J1: Status
A2: EP-1 | B2: Epic | C2: EP-1 | E2: Checkout & Payment Reliability | F2: High | I2: Product Manager | J2: In Progress
A3: EP-2 | B3: Epic | C3: EP-2 | E3: Inventory Accuracy | F3: High | I3: Product Manager | J3: In Progress
A4: EP-3 | B4: Epic | C4: EP-3 | E4: Order Tracking & Notifications | F4: High | I4: Product Manager | J4: In Progress
A5: EP-4 | B5: Epic | C5: EP-4 | E5: Fulfilment & Delivery SLA | F5: High | I5: Product Manager | J5: In Progress
A6: EP-5 | B6: Epic | C6: EP-5 | E6: Cancellation, Returns & Refunds | F6: High | I6: Product Manager | J6: In Progress
A7: EP-6 | B7: Epic | C7: EP-6 | E7: Support Tools, Audit & Analytics | F7: High | I7: Product Manager | J7: In Progress
A8: US-01 | B8: Story | C8: EP-1 | D8: FR-01 | E8: customer, I want my order confirmed only after my payment succeeds | F8: High | G8: 5 | H8: Sprint 1 | I8: Dev Team | J8: To Do
A9: US-02 | B9: Story | C9: EP-1 | D9: FR-02 | E9: customer, I want to retry or switch my payment method after a failure | F9: High | G9: 8 | H9: Sprint 1 | I9: Dev Team | J9: To Do
A10: US-03 | B10: Story | C10: EP-2 | D10: FR-03 | E10: customer, I want stock checked and held while I pay | F10: High | G10: 8 | H10: Sprint 1 | I10: Dev Team | J10: To Do
A11: US-04 | B11: Story | C11: EP-2 | D11: FR-04 | E11: customer, I want to see out-of-stock items clearly | F11: High | G11: 3 | H11: Sprint 1 | I11: Dev Team | J11: To Do
A12: US-05 | B12: Story | C12: EP-3 | D12: FR-05 | E12: operations manager, I want a single status lifecycle with timestamps | F12: High | G12: 5 | H12: Sprint 2 | I12: Dev Team | J12: To Do
A13: US-06 | B13: Story | C13: EP-3 | D13: FR-06 | E13: customer, I want to track my order status | F13: High | G13: 5 | H13: Sprint 2 | I13: Dev Team | J13: To Do
A14: US-07 | B14: Story | C14: EP-3 | D14: FR-07 | E14: customer, I want proactive updates on my order | F14: Medium | G14: 5 | H14: Sprint 3 | I14: Dev Team | J14: To Do
A15: US-08 | B15: Story | C15: EP-4 | D15: FR-08 | E15: warehouse executive, I want orders auto-allocated to the nearest stocked warehouse | F15: High | G15: 8 | H15: Sprint 2 | I15: Dev Team | J15: To Do
A16: US-09 | B16: Story | C16: EP-4 | D16: FR-09 | E16: operations manager, I want carriers assigned by pincode performance | F16: Medium | G16: 8 | H16: Sprint 3 | I16: Dev Team | J16: To Do
A17: US-10 | B17: Story | C17: EP-4 | D17: FR-10 | E17: operations manager, I want to be alerted when an order may miss its promised date | F17: High | G17: 5 | H17: Sprint 2 | I17: Dev Team | J17: To Do
A18: US-11 | B18: Story | C18: EP-5 | D18: FR-11 | E18: customer, I want to cancel an order before it ships | F18: High | G18: 5 | H18: Sprint 3 | I18: Dev Team | J18: To Do
A19: US-12 | B19: Story | C19: EP-5 | D19: FR-12 | E19: customer, I want to raise a return request online | F19: Medium | G19: 5 | H19: Sprint 3 | I19: Dev Team | J19: To Do
... A37: BUG-05 | B37: Bug | C37: EP-5 | D37: US-13 | E37: Refund amount excludes shipping fee for cancelled orders | F37: High | G37: 3 | H37: Sprint 4 | I37: Developer | J37: Open

Sheet Sprint Plan
A1: Sprint | B1: Duration | C1: Goal | D1: Stories | E1: Total Story Points | F1: Bugs open
A2: Sprint 1 | B2: Weeks 1-2 | C2: Payment & inventory foundation (checkout reliability) | D2: =COUNTIFS('Jira Backlog'!$H:$H,A2,'Jira Backlog'!$B:$B,"Story") -> 4 | E2: =SUMIFS('Jira Backlog'!$G:$G,'Jira Backlog'!$H:$H,A2) -> 44 | F2: =COUNTIFS('Jira Backlog'!$H:$H,A2,'Jira Backlog'!$B:$B,"Bug") -> 2
A3: Sprint 2 | B3: Weeks 3-4 | C3: Status lifecycle, tracking page, allocation, SLA alerts | D3: =COUNTIFS('Jira Backlog'!$H:$H,A3,'Jira Backlog'!$B:$B,"Story") -> 4 | E3: =SUMIFS('Jira Backlog'!$G:$G,'Jira Backlog'!$H:$H,A3) -> 30 | F3: =COUNTIFS('Jira Backlog'!$H:$H,A3,'Jira Backlog'!$B:$B,"Bug") -> 1
A4: Sprint 3 | B4: Weeks 5-6 | C4: Notifications, carrier assignment, cancellation, returns | D4: =COUNTIFS('Jira Backlog'!$H:$H,A4,'Jira Backlog'!$B:$B,"Story") -> 4 | E4: =SUMIFS('Jira Backlog'!$G:$G,'Jira Backlog'!$H:$H,A4) -> 28 | F4: =COUNTIFS('Jira Backlog'!$H:$H,A4,'Jira Backlog'!$B:$B,"Bug") -> 1
A5: Sprint 4 | B5: Weeks 7-8 | C5: Refund automation, support 360, audit, dashboard, UAT & go-live prep | D5: =COUNTIFS('Jira Backlog'!$H:$H,A5,'Jira Backlog'!$B:$B,"Story") -> 5 | E5: =SUMIFS('Jira Backlog'!$G:$G,'Jira Backlog'!$H:$H,A5) -> 37 | F5: =COUNTIFS('Jira Backlog'!$H:$H,A5,'Jira Backlog'!$B:$B,"Bug") -> 1
A6: Total | D6: =SUM(D2:D5) -> 17 | E6: =SUM(E2:E5) -> 139 | F6: =SUM(F2:F5) -> 5

Sheet UAT
A1: Test Case ID | B1: FR | C1: User Story | D1: Scenario | E1: Steps / Precondition | F1: Expected Result | G1: Actual Result | H1: Status | I1: Defect ID
A2: TC-01 | B2: FR-01 | C2: US-01 | D2: Successful payment (UPI) | E2: Cart with in-stock item; pay via UPI success | F2: Order created, status Confirmed, confirmation sent | G2: Order created, status Confirmed, confirmation sent | H2: Pass
A3: TC-02 | B3: FR-01 | C3: US-01 | D3: Failed payment | E3: Cart; gateway returns failure | F3: Order not confirmed; stays Payment Pending | G3: Order not confirmed; stays Payment Pending | H3: Pass
A4: TC-03 | B4: FR-02 | C4: US-02 | D4: Retry with different method | E4: After TC-02 choose Credit Card within 30 min | F4: Same cart retained; order Confirmed on success | G4: Same cart retained; order Confirmed | H4: Pass
A5: TC-04 | B5: FR-02 | C5: US-02 | D5: Double-click on Pay (idempotency) | E5: Click Pay twice within 5 seconds | F5: Customer charged once | G5: Customer charged twice | H5: Fail | I5: BUG-01
A6: TC-05 | B6: FR-03 | C6: US-03 | D6: Stock reserved during payment | E6: Qty 1 of last unit; start payment | F6: Unit reserved for 15 min; second buyer sees out of stock | G6: Unit reserved; second buyer blocked | H6: Pass
A7: TC-06 | B7: FR-03 | C7: US-03 | D7: Reservation release on timeout | E7: Start payment, abandon for 16 min | F7: Reservation released; stock available again | G7: Stock still shown reserved after 16 min | H7: Fail | I7: BUG-02
A8: TC-07 | B8: FR-04 | C8: US-04 | D8: Out-of-stock product | E8: Open product with stock = 0 | F8: Order blocked; 'Notify me' shown | G8: Order blocked; 'Notify me' shown | H8: Pass
A9: TC-08 | B9: FR-04 | C9: US-04 | D9: Stock runs out during checkout | E9: Two users buy last unit simultaneously | F9: Second order blocked with message | G9: Second order blocked with message | H9: Pass
A10: TC-09 | B10: FR-05 | C10: US-05 | D10: Valid status transition | E10: Move Packed to Shipped | F10: Status updated with timestamp | G10: Status updated with timestamp | H10: Pass
A11: TC-10 | B11: FR-05 | C11: US-05 | D11: Invalid status transition | E11: Try Delivered to Packed | F11: System rejects the change | G11: System rejects the change | H11: Pass
A12: TC-11 | B12: FR-06 | C12: US-06 | D12: Customer tracks order | E12: Open My Orders for a shipped order | F12: Shows current status and ETA | G12: Shows current status and ETA | H12: Pass
A13: TC-12 | B13: FR-06 | C13: US-06 | D13: Tracking after delivery | E13: Carrier posts Delivered | F13: Tracking page shows Delivered | G13: Tracking page still shows Shipped | H13: Fail | I13: BUG-03
A14: TC-13 | B14: FR-07 | C14: US-07 | D14: Shipped notification | E14: Order moves to Shipped | F14: SMS/e-mail sent within 5 minutes | G14: SMS/e-mail sent within 5 minutes | H14: Pass
A15: TC-14 | B15: FR-08 | C15: US-08 | D15: Warehouse auto-allocation | E15: Confirm order from Delhi with stock in Delhi and Mumbai | F15: Assigned to Delhi warehouse | G15: Assigned to Delhi warehouse | H15: Pass
A16: TC-15 | B16: FR-09 | C16: US-09 | D16: Carrier assignment by pincode | E16: Create shipment to a pincode with carrier scores | F16: Best-scoring carrier assigned | G16: Best-scoring carrier assigned | H16: Pass
A17: TC-16 | B17: FR-10 | C17: US-10 | D17: Delay flag | E17: Order Confirmed, not shipped for 49 hours | F17: Flagged 'At Risk' on Ops dashboard | G17: Flagged 'At Risk' on Ops dashboard | H17: Pass
A18: TC-17 | B18: FR-11 | C18: US-11 | D18: Cancel before shipment | E18: Cancel a Confirmed order | F18: Status Cancelled; refund initiated | G18: Status Cancelled; refund initiated | H18: Pass
A19: TC-18 | B19: FR-11 | C19: US-11 | D19: Cancel after shipment | E19: Open a Shipped order | F19: Cancel option not available | G19: Cancel option visible | H19: Fail | I19: BUG-04
A20: TC-19 | B20: FR-12 | C20: US-12 | D20: Return within window | E20: Delivered 3 days ago; raise return | F20: Return accepted; pickup slot confirmed | G20: Return accepted; pickup slot confirmed | H20: Pass
A21: TC-20 | B21: FR-12 | C21: US-12 | D21: Return outside window | E21: Delivered 10 days ago; raise return | F21: Return rejected with policy message | G21: Return rejected with policy message | H21: Pass
A22: TC-21 | B22: FR-13 | C22: US-13 | D22: Refund after QC pass | E22: Return QC = pass | F22: Refund to original source within 1 business day | G22: Refund initiated to original source | H22: Pass
A23: TC-22 | B23: FR-14 | C23: US-14 | D23: Order 360 view | E23: Agent searches order ID | F23: Payment, shipment, inventory and history shown | G23: Payment, shipment, inventory and history shown | H23: Pass
A24: TC-23 | B24: FR-15 | C24: US-15 | D24: Inventory adjustment | E24: Cycle count differs from system | F24: Adjustment logged with reason/approver; stock updated | G24: Adjustment logged with reason/approver; stock updated | H24: Pass
A25: TC-24 | B25: FR-16 | C25: US-16 | D25: Dashboard refresh | E25: Load new day of data | F25: KPIs refresh within 15 minutes | G25: KPIs refreshed in 9 minutes | H25: Pass
A26: TC-25 | B26: FR-17 | C26: US-17 | D26: Audit log | E26: Change an order status | F26: Log entry with user, time, old and new value | G26: Log entry with user, time, old and new value | H26: Pass
A28: Note: UAT executed on a hypothetical prototype for portfolio purposes; actual results are illustrative to demonstrate defect logging and traceability.

Sheet RTM
A1: Business Requirement | B1: Functional Requirement | C1: User Story | D1: Test Case | E1: Test Result (live from UAT) | F1: Defect
A2: BR-02 - Recover revenue lost to failed payments | B2: FR-01 - Create an order as 'Confirmed' only after payment success (or COD confirmation); failed payment leaves order in 'Payment Pending'. | C2: US-01 | D2: TC-01 | E2: =IFERROR(INDEX(UAT!$H:$H,MATCH(D2,UAT!$A:$A,0)),"Not Run") -> Pass | F2: =IFERROR(INDEX(UAT!$I:$I,MATCH(D2,UAT!$A:$A,0))&"","")
A3: BR-02 - Recover revenue lost to failed payments | B3: FR-01 - Create an order as 'Confirmed' only after payment success (or COD confirmation); failed payment leaves order in 'Payment Pending'. | C3: US-01 | D3: TC-02 | E3: =IFERROR(INDEX(UAT!$H:$H,MATCH(D3,UAT!$A:$A,0)),"Not Run") -> Pass | F3: =IFERROR(INDEX(UAT!$I:$I,MATCH(D3,UAT!$A:$A,0))&"","")
A4: BR-02 - Recover revenue lost to failed payments | B4: FR-02 - Allow payment retry and switching to an alternate method within 30 minutes without re-entering the cart; payments must be idempotent (no double charge). | C4: US-02 | D4: TC-03 | E4: =IFERROR(INDEX(UAT!$H:$H,MATCH(D4,UAT!$A:$A,0)),"Not Run") -> Pass | F4: =IFERROR(INDEX(UAT!$I:$I,MATCH(D4,UAT!$A:$A,0))&"","")
A5: BR-02 - Recover revenue lost to failed payments | B5: FR-02 - Allow payment retry and switching to an alternate method within 30 minutes without re-entering the cart; payments must be idempotent (no double charge). | C5: US-02 | D5: TC-04 | E5: =IFERROR(INDEX(UAT!$H:$H,MATCH(D5,UAT!$A:$A,0)),"Not Run") -> Fail | F5: =IFERROR(INDEX(UAT!$I:$I,MATCH(D5,UAT!$A:$A,0))&"","") -> BUG-01
A6: BR-03 - Make inventory accurate in real time | B6: FR-03 - Check live stock and reserve quantity at checkout; release the reservation if payment fails or times out. | C6: US-03 | D6: TC-05 | E6: =IFERROR(INDEX(UAT!$H:$H,MATCH(D6,UAT!$A:$A,0)),"Not Run") -> Pass | F6: =IFERROR(INDEX(UAT!$I:$I,MATCH(D6,UAT!$A:$A,0))&"","")
A7: BR-03 - Make inventory accurate in real time | B7: FR-03 - Check live stock and reserve quantity at checkout; release the reservation if payment fails or times out. | C7: US-03 | D7: TC-06 | E7: =IFERROR(INDEX(UAT!$H:$H,MATCH(D7,UAT!$A:$A,0)),"Not Run") -> Fail | F7: =IFERROR(INDEX(UAT!$I:$I,MATCH(D7,UAT!$A:$A,0))&"","") -> BUG-02
A8: BR-03 - Make inventory accurate in real time | B8: FR-04 - Block checkout for out-of-stock items and offer 'Notify me' / similar products. | C8: US-04 | D8: TC-07 | E8: =IFERROR(INDEX(UAT!$H:$H,MATCH(D8,UAT!$A:$A,0)),"Not Run") -> Pass | F8: =IFERROR(INDEX(UAT!$I:$I,MATCH(D8,UAT!$A:$A,0))&"","")
A9: BR-03 - Make inventory accurate in real time | B9: FR-04 - Block checkout for out-of-stock items and offer 'Notify me' / similar products. | C9: US-04 | D9: TC-08 | E9: =IFERROR(INDEX(UAT!$H:$H,MATCH(D9,UAT!$A:$A,0)),"Not Run") -> Pass | F9: =IFERROR(INDEX(UAT!$I:$I,MATCH(D9,UAT!$A:$A,0))&"","")
A10: BR-04 - Give customers and staff full order-status visibility | B10: FR-05 - Maintain a single order status lifecycle (Placed > Confirmed > Packed > Shipped > Out for Delivery > Delivered, plus Cancelled/Returned) with a timestamp for every change. | C10: US-05 | D10: TC-09 | E10: =IFERROR(INDEX(UAT!$H:$H,MATCH(D10,UAT!$A:$A,0)),"Not Run") -> Pass | F10: =IFERROR(INDEX(UAT!$I:$I,MATCH(D10,UAT!$A:$A,0))&"","")
A11: BR-04 - Give customers and staff full order-status visibility | B11: FR-05 - Maintain a single order status lifecycle (Placed > Confirmed > Packed > Shipped > Out for Delivery > Delivered, plus Cancelled/Returned) with a timestamp for every change. | C11: US-05 | D11: TC-10 | E11: =IFERROR(INDEX(UAT!$H:$H,MATCH(D11,UAT!$A:$A,0)),"Not Run") -> Pass | F11: =IFERROR(INDEX(UAT!$I:$I,MATCH(D11,UAT!$A:$A,0))&"","")
A12: BR-04 - Give customers and staff full order-status visibility | B12: FR-06 - Provide a customer order-tracking page showing current status and estimated delivery date. | C12: US-06 | D12: TC-11 | E12: =IFERROR(INDEX(UAT!$H:$H,MATCH(D12,UAT!$A:$A,0)),"Not Run") -> Pass | F12: =IFERROR(INDEX(UAT!$I:$I,MATCH(D12,UAT!$A:$A,0))&"","")
A13: BR-04 - Give customers and staff full order-status visibility | B13: FR-06 - Provide a customer order-tracking page showing current status and estimated delivery date. | C13: US-06 | D13: TC-12 | E13: =IFERROR(INDEX(UAT!$H:$H,MATCH(D13,UAT!$A:$A,0)),"Not Run") -> Fail | F13: =IFERROR(INDEX(UAT!$I:$I,MATCH(D13,UAT!$A:$A,0))&"","") -> BUG-03
... A26: BR-04 - Give customers and staff full order-status visibility | B26: FR-17 - Keep an audit log of all order, payment and inventory state changes (who/what/when). | C26: US-17 | D26: TC-25 | E26: =IFERROR(INDEX(UAT!$H:$H,MATCH(D26,UAT!$A:$A,0)),"Not Run") -> Pass | F26: =IFERROR(INDEX(UAT!$I:$I,MATCH(D26,UAT!$A:$A,0))&"","")
